anarchy/__init__.py
anarchy/anarchy.py
anarchy/edge.py
anarchy/graph.py
anarchy/node.py
anarchy/search.py
anarchy/util.py
tests/__init__.py
tests/test_anarchy.py
tests/test_edge.py
tests/test_graph.py
tests/test_node.py
anarchygraph-0.1.8.dist-info/METADATA
anarchygraph-0.1.8.dist-info/WHEEL
anarchygraph-0.1.8.dist-info/top_level.txt
anarchygraph-0.1.8.dist-info/RECORD
