Metadata-Version: 2.1
Name: anarchygraph
Version: 0.1.8
Summary: A decentralized graph system to simulate agents in an artificial reality.
Home-page: https://pypi.org/project/anarchygraph/
Author: Chris Mangum
Author-email: csmangum@gmail.com
Classifier: Programming Language :: Python :: 3
Classifier: License :: OSI Approved :: MIT License
Classifier: Operating System :: OS Independent
Requires-Python: >=3.10
Requires-Dist: ipycytoscape
Requires-Dist: hypothesis
Requires-Dist: pytest
Requires-Dist: pyperf
